Workbook

Sheet Revenue Workings
B2: =[1]PL!A2 -> Entity Name
B3: Revenue Workings
B5: Particulars | C5: Amount
B6: Remuneration Cost | C6: 0
B7: Payroll provisions | C7: 0
B8: Employee Insurance | C8: 0
B9: Transportation | C9: 0
B10: Staff Welfare | C10: 0
B11: Communication expenses | C11: 0
B12: Office maintenance | C12: 0
B13: Travel | C13: 0
B14: ANSR Fees | C14: 0
B15: Recruitment Expenses | C15: 0
B16: Professional fees | C16: 0
B17: Corporate Social Responsibility | C17: 0
... B26: Amortization | C26: 0
B28: Total Cost | C28: =SUM(C6:C26) -> 0
B29: Mark Up @ XX% | C29: =C28*17% -> 0
B30: Total Revenue | C30: =C28+C29 -> 0
B31: Tax Expense | C31: =C29*22%*1.1*1.04 -> 0
B33: Expenses not included for the purpose of calculation of revenue as per intercompany agreement
B34: 740021 Exchange fluctuation - realized | C34: 0
B35: Total | C35: =SUM(C34:C34) -> 0
B37: Expense as per P&L | C37: =[1]PL!G38+[1]PL!G28+[1]PL!G12 -> 0
B38: Differnce | C38: =C28+C35-C37 -> 0
B40: Invoice raised | C40: 0
B41: Less: Unbillled revenue for the month of March 22 | C41: 0
B42: Net revenue for current month | C42: =C40+C41 -> 0

Sheet Accrued Expenses
B2: ='Revenue Workings'!B2 -> Entity Name
B3: Schedule Name - Accrued Expenses
B5: Name of the Vendor | C5: Nature of expense | D5: 0 - 60 Days | E5: 61 to 90 Days | F5: 91 to 120 Days | G5: 121 to 180 Days | H5: 180 Days and above
B6: ANSR Global Corporation Private Limited | C6: Postage & Courier | D6: 0 | E6: 0 | F6: 0 | G6: 0 | H6: 0
B7: ANSR Global Corporation Private Limited | C7: Office Consumables | D7: 0 | E7: 0 | F7: 0 | G7: 0 | H7: 0
B8: TBD | C8: Audit fee and filing for FY 2022-23 | D8: 0 | E8: 0 | F8: 0 | G8: 0 | H8: 0
B9: TBD | C9: Statutory audit of the Company under Indian GAAP | D9: 0 | E9: 0 | F9: 0 | G9: 0 | H9: 0
B10: TBD | C10: Tax financials, if applicable | D10: 0 | E10: 0 | F10: 0 | G10: 0 | H10: 0
B11: TBD | C11: Annual GST return (GSTR9 & GSTR9C) | D11: 0 | E11: 0 | F11: 0 | G11: 0 | H11: 0
B12: TBD | C12: Annual Performance Report (SEZ) | D12: 0 | E12: 0 | F12: 0 | G12: 0 | H12: 0
B13: TBD | C13: Certification of form 56F | D13: 0 | E13: 0 | F13: 0 | G13: 0 | H13: 0
B14: TBD | C14: Certification of form 29C / 28B | D14: 0 | E14: 0 | F14: 0 | G14: 0 | H14: 0
B15: TBD | C15: Transfer Pricing Study Report | D15: 0 | E15: 0 | F15: 0 | G15: 0 | H15: 0
B16: TBD | C16: Annual Income Tax return preparation and filing | D16: 0 | E16: 0 | F16: 0 | G16: 0 | H16: 0
B17: TBD | C17: Filing of Statement of Financial Transactions | D17: 0 | E17: 0 | F17: 0 | G17: 0 | H17: 0
... B19: Corporate Social Responsibility | C19: Advance CSR Expense | D19: 0 | E19: 0 | F19: 0 | G19: 0 | H19: 0
C20: Total | D20: =SUM(D6:D19) -> 0 | E20: =SUM(E6:E19) -> 0 | F20: =SUM(F6:F19) -> 0 | G20: =SUM(G6:G19) -> 0 | H20: =SUM(H6:H19) -> 0

Sheet Inter Company Payable
B2: ='Accrued Expenses'!B2 -> Entity Name
B3: Schedule Name - 2024 - Inter-Company Payables
B5: Date | C5: Particulars | D5: Purpose | E5: Amount in USD | F5: Amount in INR
C6: Parent Company | D6: Advance Received | E6: 0 | F6: 0
C9: Total | E9: =SUM(E6:E8) -> 0 | F9: =SUM(F6:F8) -> 0

Sheet Accounts Payable
B2: ='Inter Company Payable'!B2 -> Entity Name
B3: Schedule Name - Accounts Payable
B5: Date | C5: Invoice Number | D5: Party's Name | E5: Pending Amount | F5: Due on | G5: Overdue by days | H5: Tally Reference | I5: Description
B33: Total | E33: =SUM(E6:E32) -> 0

Sheet Employee payables
B2: ='Accounts Payable'!B2 -> Entity Name
B3: Schedule Name - Employee Payables
B4: Particulars | C4: Month
B5: 2003 - Payroll Payable | C5: 0
B6: 2003 - Payroll Payable (Hold or FNFS) | C6: 0
B7: 2004 - Bonus Payable | C7: 0
B8: 2005 - Leave Encashment Liability | C8: 0
B9: Total | C9: =SUM(C5:C8) -> 0

Sheet Statutory Liability - Employees
B2: ='Employee payables'!B2 -> Entity Name
B3: Statutory Liability - Employees
B4: Sl. No | C4: Particulars | D4: Month
B5: 1 | C5: 2012 - Provident Fund - Employers Contribution Payable | D5: 0
B6: 2 | C6: 2013 - Provident Fund - Employees Contribution Payable | D6: 0
B7: 3 | C7: 2014 - Profession Tax Payable | D7: 0
B8: Total | D8: =SUM(D5:D7) -> 0

Sheet Witholding taxes
B2: ='Statutory Liability - Employees'!$B$2 -> Entity Name
B3: Witholding taxes
B4: SL No | C4: Particulars | D4: Amount
B5: 1 | C5: 2019 - Taxes Deducted At Source - 192 Salary | D5: 0
B6: 2 | C6: 2019 - Taxes Deducted At Source - 194 C Contractors | D6: 0
B7: 3 | C7: 2019 - Taxes Deducted At Source - 194 J Professional Fees | D7: 0
B8: 4 | C8: 2019 - Taxes Deducted At Source - 194 I Rent | D8: 0
B9: 5 | C9: 2019 - Taxes Deducted At Source - 194 H Commission | D9: 0
B10: 6 | C10: 2019 - Taxes Deducted At Source - 194 Q Goods | D10: 0
B11: 7 | C11: 2019 - Taxes Deducted At Source - 195 Non Residents | D11: 0
B12: Total Amount | D12: =SUM(D5:D11) -> 0

Sheet Bank Balance
B2: ='Witholding taxes'!$B$2 -> Entity Name
B3: 1001 - Bank Current Account - INR
B5: Particulars | C5: Balance as per books | D5: Balance as per bank statement | E5: Difference | F5: Remarks
B6: Account number | C6: 0 | D6: =C6 -> 0 | E6: =C6-D6 -> 0 | F6: Bank Statement to be attached

Sheet Other Receivables
B2: {='Bank Balance'!B2:D2} -> Entity Name | C2: 0 | D2: 0
B3: Schedule Name - Other Recivables
B5: Supposed to be Accounted as per CD working
B6: Month | C6: GMC | D6: DCL | E6: DCL (CI) | F6: Total
B7: 44652 | C7: 0 | D7: 0 | E7: 0 | F7: =SUM(C7:E7) -> 0
B8: 44682 | C8: 0 | D8: 0 | E8: 0 | F8: =SUM(C8:E8) -> 0
B9: 44713 | C9: 0 | D9: 0 | E9: 0 | F9: =SUM(C9:E9) -> 0
B10: 44743 | C10: 0 | D10: 0 | E10: 0 | F10: =SUM(C10:E10) -> 0
B11: 44774 | C11: 0 | D11: 0 | E11: 0 | F11: =SUM(C11:E11) -> 0
B12: 44805 | C12: 0 | D12: 0 | E12: 0 | F12: =SUM(C12:E12) -> 0
B13: 44835 | C13: 0 | D13: 0 | E13: 0 | F13: =SUM(C13:E13) -> 0
B14: 44866 | C14: 0 | D14: 0 | E14: 0 | F14: =SUM(C14:E14) -> 0
B15: 44896 | C15: 0 | D15: 0 | E15: 0 | F15: =SUM(C15:E15) -> 0
B16: 45292 | C16: 0 | D16: 0 | E16: 0 | F16: =SUM(C16:E16) -> 0
B17: 45323 | C17: 0 | D17: 0 | E17: 0 | F17: =SUM(C17:E17) -> 0
B18: 45352 | C18: 0 | D18: 0 | E18: 0 | F18: =SUM(C18:E18) -> 0
B19: TOTAL | C19: =SUM(C7:C18) -> 0 | D19: =SUM(D7:D18) -> 0 | E19: =SUM(E7:E18) -> 0 | F19: =SUM(F7:F18) -> 0
B20: Total Amount Paid
B21: Amortisation | F21: =-F19 -> 0
B22: Total prepaid expenses | F22: =SUM(F20:F21) -> 0

Sheet Loans & Advances
B2: ='Other Receivables'!B2 -> Entity Name
B3: 1016 - Advance Tax
B5: Particulars | C5: FY 2022-23 | D5: FY 2023-24 | E5: Remarks
B6: Advance Tax Paid | C6: 0 | D6: 0
B7: Provision for income tax | C7: 0 | D7: 0
B8: Q1 Advance Tax Paid | C8: 0 | D8: 0
B9: Q2 Advance Tax Paid | C9: 0 | D9: 0
B10: Q3 Advance Tax Paid | C10: 0 | D10: 0
B11: Q4 Advance Tax Paid | C11: 0 | D11: 0
B12: Total | C12: =SUM(C6:C11) -> 0 | D12: =SUM(D6:D11) -> 0

Sheet Employee Provisions
B2: ='Loans & Advances'!B2 -> Entity Name
B3: 2007 - Gratuity Liability
B5: Particular | C5: Month | D5: Amount
B6: Gratuity Liability | C6: 45017 | D6: 0
B7: Gratuity Liability | C7: 45047 | D7: 0
B8: Gratuity Liability | C8: 45078 | D8: 0
B9: Gratuity Liability | C9: 45108 | D9: 0
B10: Gratuity Liability | C10: 45139 | D10: 0
B11: Gratuity Liability | C11: 45170 | D11: 0
B12: Gratuity Liability | C12: 45200 | D12: 0
B13: Gratuity Liability | C13: 45231 | D13: 0
B14: Gratuity Liability | C14: 45261 | D14: 0
B15: Gratuity Liability | C15: 45292 | D15: 0
B16: Gratuity Liability | C16: 45323 | D16: 0
B17: Gratuity Liability | C17: 45352 | D17: 0
B18: Total | D18: =SUM(D6:D10) -> 0

Sheet Provision for Income tax
B2: ='Employee Provisions'!B2 -> Entity Name
B3: 2011 - Provision For Income Tax
B5: 230101 Provision for Income Tax
B6: Particular | C6: Nature of Expences | D6: Month | E6: Amount | F6: Remarks
B7: Provision for income tax | C7: Tax Liability | D7: 45017 | E7: 0
B8: Provision for income tax | C8: Tax Liability | D8: 45047 | E8: 0
B9: Provision for income tax | C9: Tax Liability | D9: 45078 | E9: 0
B10: Provision for income tax | C10: Tax Liability | D10: 45108 | E10: 0
B11: Provision for income tax | C11: Tax Liability | D11: 45139 | E11: 0
B12: Provision for income tax | C12: Tax Liability | D12: 45170 | E12: 0
B13: Provision for income tax | C13: Tax Liability | D13: 45200 | E13: 0
B14: Provision for income tax | C14: Tax Liability | D14: 45231 | E14: 0
B15: Provision for income tax | C15: Tax Liability | D15: 45261 | E15: 0
B16: Provision for income tax | C16: Tax Liability | D16: 45292 | E16: 0
B17: Provision for income tax | C17: Tax Liability | D17: 45323 | E17: 0
B18: Provision for income tax | C18: Tax Liability | D18: 45352 | E18: 0
B19: Total | E19: =SUM(E7:E18) -> 0
